p6_barrier/__init__.py
p6_barrier/py.typed
p6_barrier/_jsii/__init__.py
p6_barrier/_jsii/p6-barrier@0.1.107.jsii.tgz
p6_barrier-0.1.107.dist-info/LICENSE
p6_barrier-0.1.107.dist-info/METADATA
p6_barrier-0.1.107.dist-info/WHEEL
p6_barrier-0.1.107.dist-info/top_level.txt
p6_barrier-0.1.107.dist-info/RECORD
