Metadata-Version: 2.1
Name: p6-barrier
Version: 0.1.107
Summary: p6-barrier
Home-page: https://github.com/p6m7g8/p6-barrier.git
Author: Philip M. Gollucci<pgollucci@p6m7g8.com>
License: Apache-2.0
Project-URL: Source, https://github.com/p6m7g8/p6-barrier.git
Platform: UNKNOWN
Classifier: Intended Audience :: Developers
Classifier: Operating System :: OS Independent
Classifier: Programming Language :: JavaScript
Classifier: Programming Language :: Python :: 3 :: Only
Classifier: Programming Language :: Python :: 3.6
Classifier: Programming Language :: Python :: 3.7
Classifier: Programming Language :: Python :: 3.8
Classifier: Programming Language :: Python :: 3.9
Classifier: Typing :: Typed
Classifier: Development Status :: 5 - Production/Stable
Classifier: License :: OSI Approved
Requires-Python: >=3.6
Requires-Dist: aws-cdk.aws-iam (<2.0.0,>=1.98.0)
Requires-Dist: aws-cdk.aws-lambda-nodejs (<2.0.0,>=1.98.0)
Requires-Dist: aws-cdk.aws-lambda (<2.0.0,>=1.98.0)
Requires-Dist: aws-cdk.aws-ssm (<2.0.0,>=1.98.0)
Requires-Dist: aws-cdk.core (<2.0.0,>=1.98.0)
Requires-Dist: aws-cdk.custom-resources (<2.0.0,>=1.98.0)
Requires-Dist: constructs (<4.0.0,>=3.2.27)
Requires-Dist: jsii (<2.0.0,>=1.28.0)
Requires-Dist: publication (>=0.0.3)
